test_mcp/__init__.py
test_mcp/main.py
test_mcp/tools/__init__.py
test_mcp/tools/eigen_tool.py
test_mcp/tools/matrix_tool.py
test_mcp/tools/quadratic_tool.py
test_mcp_poojithamm-0.1.0.dist-info/METADATA
test_mcp_poojithamm-0.1.0.dist-info/WHEEL
test_mcp_poojithamm-0.1.0.dist-info/entry_points.txt
test_mcp_poojithamm-0.1.0.dist-info/top_level.txt
test_mcp_poojithamm-0.1.0.dist-info/RECORD
