Metadata-Version: 2.4
Name: test-mcp-poojithamm
Version: 0.1.0
Summary: Test MCP tools
Author-email: Poojitha29 <poojitha.mm@thoughtclan.com>
Requires-Python: >=3.9
Requires-Dist: mcp-math-tools>=0.1.0
Requires-Dist: numpy>=1.24.0
Requires-Dist: sympy>=1.12
Provides-Extra: cli
Requires-Dist: mcp[cli]>=1.12.3; extra == "cli"
